dontuserepl/__init__.py
dontuserepl/keep_alive.py
dontuserepl/lazy.py
dontuserepl/uptimerobot/__init__.py
dontuserepl/uptimerobot/api.py
dontuserepl/uptimerobot/monitor.py
dontuserepl/vars.py
dontuserepl-0.1.5.dist-info/WHEEL
dontuserepl-0.1.5.dist-info/METADATA
dontuserepl-0.1.5.dist-info/RECORD
