Metadata-Version: 2.1
Name: dontuserepl
Version: 0.1.5
Summary: Simple tools to deploy a script 24/7 on repl.it using an aiohttp server and automated uptimerobot monitors
Home-page: https://github.com/chrisdewa/dontuserepl
License: MIT
Author: chrisdewa
Author-email: alexdewa@gmail.com
Requires-Python: >=3.8,<4.0
Classifier: Development Status :: 4 - Beta
Classifier: Intended Audience :: Developers
Classifier: License :: OSI Approved :: MIT License
Classifier: Programming Language :: Python :: 3
Classifier: Programming Language :: Python :: 3.8
Classifier: Programming Language :: Python :: 3.9
Requires-Dist: aiohttp (==3.7.4.post0)
Requires-Dist: aiolimiter (==1.0.0b1)
Project-URL: Repository, https://github.com/chrisdewa/dontuserepl
